StreamlinkUtils/__init__.py
streamlinkutils-0.0.2.dist-info/entry_points.txt
streamlinkutils-0.0.2.dist-info/LICENSE
streamlinkutils-0.0.2.dist-info/METADATA
streamlinkutils-0.0.2.dist-info/WHEEL
streamlinkutils-0.0.2.dist-info/RECORD
