Metadata-Version: 2.1
Name: streamlinkutils
Version: 0.0.2
Summary: This module adds extra utilities to Streamlink's API. I am in no way connected with Streamlink.
Author: Parrot Developers
Author-email: redacted@example.com
Requires-Python: >=3.9,<4.0
Classifier: Programming Language :: Python :: 3
Classifier: Programming Language :: Python :: 3.9
Classifier: Programming Language :: Python :: 3.10
Classifier: Programming Language :: Python :: 3.11
Requires-Dist: streamlink (>=2.4.0,<3.0.0)
